lofo/__init__.py
lofo/dataset.py
lofo/flofo_importance.py
lofo/infer_defaults.py
lofo/lofo_importance.py
lofo/plotting.py
lofo/utils.py
lofo_importance-0.3.4.dist-info/LICENSE
lofo_importance-0.3.4.dist-info/METADATA
lofo_importance-0.3.4.dist-info/WHEEL
lofo_importance-0.3.4.dist-info/top_level.txt
lofo_importance-0.3.4.dist-info/RECORD
