Metadata-Version: 2.1
Name: lofo-importance
Version: 0.3.4
Summary: Leave One Feature Out Importance
Home-page: https://github.com/aerdem4/lofo-importance
Author: Ahmet Erdem
Author-email: ahmeterd4@gmail.com
Keywords: feature importance selection explainable data-science machine-learning
Classifier: Programming Language :: Python :: 3
Classifier: License :: OSI Approved :: MIT License
Classifier: Operating System :: OS Independent
License-File: LICENSE
Requires-Dist: numpy >=1.17.3
Requires-Dist: pandas
Requires-Dist: scipy
Requires-Dist: scikit-learn >=0.20.3
Requires-Dist: tqdm
Requires-Dist: lightgbm
Requires-Dist: networkx
